{"version":1,"resource":"file:///home/coumbisse9104/exoGPT/exofetch.html","entries":[{"id":"ap7x.html","timestamp":1755627754374},{"id":"sVzt.html","timestamp":1755684438422},{"id":"Ftqn.html","timestamp":1755684622468},{"id":"GvmY.html","timestamp":1755687706389},{"id":"P8lN.html","timestamp":1755687964609},{"id":"FKEW.html","timestamp":1755864541476},{"id":"HSxL.html","source":"undoRedo.source","timestamp":1755864549511},{"id":"f8ge.html","source":"undoRedo.source","timestamp":1755864561408}]}